idios/__init__.py
idios/app.py
idios-0.3.0.dist-info/WHEEL
idios-0.3.0.dist-info/entry_points.txt
idios-0.3.0.dist-info/METADATA
idios-0.3.0.dist-info/RECORD
