Metadata-Version: 2.3
Name: idios
Version: 0.3.0
Summary: A terminal code editor for those of us who aren't into vim.
Author: Daniel Roy Greenfeld
Author-email: Daniel Roy Greenfeld <daniel@feldroy.com>
Requires-Dist: textual[syntax]>=3.0.0
Requires-Dist: typer>=0.21.0
Requires-Python: >=3.14
